odoo/addons/hr_employee_phone_pin/README.rst
odoo/addons/hr_employee_phone_pin/__init__.py
odoo/addons/hr_employee_phone_pin/__manifest__.py
odoo/addons/hr_employee_phone_pin/i18n/es.po
odoo/addons/hr_employee_phone_pin/i18n/hr_employee_phone_pin.pot
odoo/addons/hr_employee_phone_pin/i18n/it.po
odoo/addons/hr_employee_phone_pin/models/__init__.py
odoo/addons/hr_employee_phone_pin/models/hr_employee.py
odoo/addons/hr_employee_phone_pin/models/hr_employee_public.py
odoo/addons/hr_employee_phone_pin/readme/CONTRIBUTORS.rst
odoo/addons/hr_employee_phone_pin/readme/DESCRIPTION.rst
odoo/addons/hr_employee_phone_pin/readme/USAGE.rst
odoo/addons/hr_employee_phone_pin/security/hr_security.xml
odoo/addons/hr_employee_phone_pin/static/description/icon.png
odoo/addons/hr_employee_phone_pin/static/description/index.html
odoo/addons/hr_employee_phone_pin/tests/__init__.py
odoo/addons/hr_employee_phone_pin/tests/test_hr_employee_phone_pin.py
odoo/addons/hr_employee_phone_pin/views/hr_employee_public_views.xml
odoo/addons/hr_employee_phone_pin/views/hr_employee_views.xml
odoo_addon_hr_employee_phone_pin-16.0.1.0.0.5.dist-info/METADATA
odoo_addon_hr_employee_phone_pin-16.0.1.0.0.5.dist-info/WHEEL
odoo_addon_hr_employee_phone_pin-16.0.1.0.0.5.dist-info/top_level.txt
odoo_addon_hr_employee_phone_pin-16.0.1.0.0.5.dist-info/RECORD
